rcdtool/log.py
rcdtool/main.py
rcdtool/rcdtool.py
rcdtool/utils.py
rcdtool-2.1.1.dist-info/licenses/LICENSE
rcdtool-2.1.1.dist-info/METADATA
rcdtool-2.1.1.dist-info/WHEEL
rcdtool-2.1.1.dist-info/entry_points.txt
rcdtool-2.1.1.dist-info/top_level.txt
rcdtool-2.1.1.dist-info/RECORD
