Metadata-Version: 2.4
Name: rcdtool
Version: 2.1.1
Summary: Script that downloads telegram restricted content.
Author-email: David Waster <wasterdavid@gmail.com>
Keywords: library,telegram,restricted,download
Classifier: Environment :: Console
Classifier: Programming Language :: Python :: 3.9
Classifier: Topic :: Communications :: Chat
Classifier: Topic :: Software Development :: Libraries
Requires-Python: >=3.9
License-File: LICENSE
Requires-Dist: Telethon
Requires-Dist: filetype
Requires-Dist: colored
Provides-Extra: dev
Requires-Dist: pytest; extra == "dev"
Dynamic: license-file
